{
    "comidas": [
        {
            "idMeal": "53036",
            "strMeal": "Pato veneciano Ragu",
            "strDrinkAlternate": "",
            "strCategory": "Pasta",
            "strArea": "italiano",
            "strInstrucciones": "",
            "strMealThumb": "https://www.themealdb.com/images/media/meals/qvrwpt1511181864.jpg",
            "strTags": "",
            "strYoutube": "https://www.youtube.com/watch?v=oWQDVgjB_Lw",
            "strIngredient": {
                "1": "Patatas harinosas",
                "2": "Mantequilla",
                "3": "Clove de ajo",
                "4": "Repollo",
                "5": "Cebollas de primavera",
                "6": "Crema Doble",
                "7": "Mostaza",
                "8": "Jamón",
                "9": "Huevos",
                "10": "",
                "11": "",
                "12": "",
                "13": "",
                "14": "",
                "15": "",
                "16": "",
                "17": "",
                "18": "",
                "19": "",
                "20": ""
            },
            "strMeasure": {
                "1": "800g",
                "2": "50 g",
                "3": "3 picados",
                "4": "1 picado",
                "5": "8",
                "6": "100ml",
                "7": "2 cucharadas",
                "8": "180 g",
                "9": "4",
                "10": " ",
                "11": " ",
                "12": " ",
                "13": " ",
                "14": " ",
                "15": " ",
                "16": " ",
                "17": " ",
                "18": " ",
                "19": " ",
                "20": " "
            },
            "strSource": "https://www.bbcgoodfood.com/recipes/venetian-duck-ragu",
            "strImageSource": "",
            "strCreativeCommonsConfirmado": ""
        }
    ]
}